[
    {
    "question" : " What is capital of India?",
    "opt1": "gandhinagar", 
    "opt2": "Surat", 
    "opt3": "Delhi", 
    "opt4": "mumbai", 
    "correct": "opt3"
},
{
    "question": " What is the capital of Thailand?",
    "opt1": "Lampang", 
    "opt2": "phuket", 
    "opt3": "Ayutthaya", 
    "opt4": "Bangkok", 
    "correct": "opt4"
},
{
    "question": " What is the capital of Gujarat",
    "opt1":  "surat",
    "opt2": "vadodara",
    "opt3": "gandhinagar",
    "opt4": "rajkot", 
    "correct": "opt3"
},
{
    "question": "Which language runs in a web browser?",
    "opt1": "Java",
    "opt2": "C",
    "opt3": "Python",
    "opt4": "javascript",
    "correct": "opt4"
},
{
    "question": "What does CSS stand for?",
    "opt1": "Central Style Sheets",
    "opt2": "Cascading Style Sheets",
    "opt3": "Cascading Simple Sheets",
    "opt4": "Cars SUVs Sailboats",
    "correct": "opt2"
},
{
    "question": "What does HTML stand for?",
    "opt1": "Hypertext Markup Language",
    "opt2": "Hypertext Markdown Language",
    "opt3": "Hyperloop Machine Language",
    "opt4": "Helicopters Terminals Motorboats Lamborginis",
    "correct": "opt1"
},
{
    "question": "What year was JavaScript launched?",
    "opt1": "1996",
    "opt2": "1995",
    "opt3": "1994",
    "opt4": "none of the above",
    "correct": "opt2"
}
]